tornado_profiler/__init__.py
tornado_profiler/profiler.py
tornado_profiler/utils.py
tornado_profiler/views.py
tornado_profiler/backend/__init__.py
tornado_profiler/backend/_sqlalchemy.py
tornado_profiler/static/favicon.ico
tornado_profiler/static/css/bootstrap.min.css
tornado_profiler/static/css/custom.css
tornado_profiler/static/css/datatables.min.css
tornado_profiler/static/css/daterangepicker.css
tornado_profiler/static/css/flat-ui.min.css
tornado_profiler/static/fonts/glyphicons-halflings-regular.ttf
tornado_profiler/static/fonts/glyphicons-halflings-regular.woff
tornado_profiler/static/fonts/glyphicons/flat-ui-icons-regular.eot
tornado_profiler/static/fonts/glyphicons/flat-ui-icons-regular.svg
tornado_profiler/static/fonts/glyphicons/flat-ui-icons-regular.ttf
tornado_profiler/static/fonts/glyphicons/flat-ui-icons-regular.woff
tornado_profiler/static/fonts/glyphicons/selection.json
tornado_profiler/static/fonts/lato/lato-black.eot
tornado_profiler/static/fonts/lato/lato-black.svg
tornado_profiler/static/fonts/lato/lato-black.ttf
tornado_profiler/static/fonts/lato/lato-black.woff
tornado_profiler/static/fonts/lato/lato-bold.eot
tornado_profiler/static/fonts/lato/lato-bold.svg
tornado_profiler/static/fonts/lato/lato-bold.ttf
tornado_profiler/static/fonts/lato/lato-bold.woff
tornado_profiler/static/fonts/lato/lato-bolditalic.eot
tornado_profiler/static/fonts/lato/lato-bolditalic.svg
tornado_profiler/static/fonts/lato/lato-bolditalic.ttf
tornado_profiler/static/fonts/lato/lato-bolditalic.woff
tornado_profiler/static/fonts/lato/lato-italic.eot
tornado_profiler/static/fonts/lato/lato-italic.svg
tornado_profiler/static/fonts/lato/lato-italic.ttf
tornado_profiler/static/fonts/lato/lato-italic.woff
tornado_profiler/static/fonts/lato/lato-light.eot
tornado_profiler/static/fonts/lato/lato-light.svg
tornado_profiler/static/fonts/lato/lato-light.ttf
tornado_profiler/static/fonts/lato/lato-light.woff
tornado_profiler-1.0.0.dist-info/METADATA
tornado_profiler-1.0.0.dist-info/RECORD
tornado_profiler-1.0.0.dist-info/WHEEL
tornado_profiler-1.0.0.dist-info/top_level.txt
