Metadata-Version: 2.1
Name: tornado-profiler
Version: 1.0.0
Summary: A profiler for Tornado Web Server
Home-page: https://github.com/garenchan/tornado-profiler
Author: garenchan
Author-email: 1412950785@qq.com
License: BSD
Platform: UNKNOWN
Classifier: License :: OSI Approved :: BSD License
Classifier: Programming Language :: Python :: 3
Classifier: Programming Language :: Python :: 3.3
Classifier: Programming Language :: Python :: 3.4
Classifier: Programming Language :: Python :: 3.5
Classifier: Programming Language :: Python :: 3.6
Classifier: Programming Language :: Python :: Implementation :: CPython
Classifier: Programming Language :: Python :: Implementation :: PyPy
Classifier: Operating System :: OS Independent
Requires-Dist: tornado (>=4.5)
